jinjafy/__init__.py
jinjafy/bibliography_maker.py
jinjafy/jinja_env.py
jinjafy/jinja_matlab_load.py
jinjafy/jinjafy.py
jinjafy/snipper.py
jinjafy/textools.py
jinjafy/cache/__init__.py
jinjafy/cache/simplecache.py
jinjafy/plot/__init__.py
jinjafy/plot/plot_helpers.py
slider/__init__.py
slider/__main__.py
slider/beamer_nup.py
slider/convert.py
slider/latexutils.py
slider/legacy_importer.py
slider/slide.py
slider/slide_fixer.py
slider/slider_cli.py
slider/slider_init.py
slider/version.py
slider/data/DTU_Beamer_files/beamer_slider_preamble.tex
slider/data/DTU_Beamer_files/beamercolorthemeDTU.sty
slider/data/DTU_Beamer_files/beamerfontthemeDTU.sty
slider/data/DTU_Beamer_files/beamerinnerthemeDTU.sty
slider/data/DTU_Beamer_files/beamerouterthemeDTU.sty
slider/data/DTU_Beamer_files/beamerthemeDTU.sty
slider/data/DTU_Beamer_files/blank.png
slider/data/DTU_Beamer_files/departments.tex
slider/data/DTU_Beamer_files/dtucolours.tex
slider/data/DTU_Beamer_files/tex_compute_uk.pdf
slider/data/DTU_Beamer_files/tex_dtu_compute_a_uk.pdf
slider/data/DTU_Beamer_files/tex_dtu_frise.pdf
slider/data/DTU_Beamer_files/tex_dtu_logo.pdf
beamer_slider-0.1.26.11.dist-info/LICENSE
beamer_slider-0.1.26.11.dist-info/METADATA
beamer_slider-0.1.26.11.dist-info/WHEEL
beamer_slider-0.1.26.11.dist-info/entry_points.txt
beamer_slider-0.1.26.11.dist-info/top_level.txt
beamer_slider-0.1.26.11.dist-info/RECORD
