Metadata-Version: 2.1
Name: beamer-slider
Version: 0.1.26.11
Summary: Software to create inkscape overlays in Beamer
Home-page: https://lab.compute.dtu.dk/tuhe/slider
Author: Tue Herlau
Author-email: tuhe@dtu.dk
License: MIT
Project-URL: Bug Tracker, https://lab.compute.dtu.dk/tuhe/slider/issues
Classifier: Programming Language :: Python :: 3
Classifier: License :: OSI Approved :: MIT License
Classifier: Operating System :: OS Independent
Requires-Python: >=3.8
License-File: LICENSE
Requires-Dist: Jinja2
Requires-Dist: numpy
Requires-Dist: chardet
Requires-Dist: scipy
Requires-Dist: seaborn
Requires-Dist: lxml
Requires-Dist: matplotlib
Requires-Dist: pylatexenc
Requires-Dist: beautifulsoup4
Requires-Dist: PyPDF2
Requires-Dist: clize
Requires-Dist: click
